runcalc
