Metadata-Version: 1.1
Name: runcalc
Version: 0.1.1
Summary: Running pace calculator
Home-page: https://github.com/mpatek/runcalc
Author: Mike Patek
Author-email: mpatek@gmail.com
License: UNKNOWN
Download-URL: https://github.com/mpatek/runcalc/tarball/0.1.1
Keywords: running,exercise,cli
Platform: UNKNOWN
